AI_text_classifier/__init__.py
AI_text_classifier/classifier.py
AI_classifier-1.0.dist-info/METADATA
AI_classifier-1.0.dist-info/WHEEL
AI_classifier-1.0.dist-info/top_level.txt
AI_classifier-1.0.dist-info/RECORD
