Metadata-Version: 2.1
Name: AI_classifier
Version: 1.0
Summary: A package for text classification using transformers models which classifies text whether it is AI generated or human written
Home-page: https://github.com/saiadupa/AI_classifier
Author: Nithin sai Adupa
Author-email: nithinsaiadupa@gmail.com
Classifier: Programming Language :: Python :: 3
Classifier: License :: OSI Approved :: MIT License
Classifier: Operating System :: OS Independent
